langgraph_equations/__init__.py
langgraph_equations/get_primitives.py
langgraph_equations/simplify.py
python_langgraph_equations-0.0.3.dist-info/licenses/LICENSE
python_langgraph_equations-0.0.3.dist-info/METADATA
python_langgraph_equations-0.0.3.dist-info/WHEEL
python_langgraph_equations-0.0.3.dist-info/top_level.txt
python_langgraph_equations-0.0.3.dist-info/RECORD
