Metadata-Version: 2.4
Name: python-langgraph-equations
Version: 0.0.3
Summary: python-langgraph-equations
Author-email: Pauli Rikula <pauli.rikula@gmail.com>
License: MIT
Project-URL: Homepage, https://github.com/kummahiih/python-langgraph-equations
Requires-Python: <4.0,>=3.6
License-File: LICENSE
Requires-Dist: python-category-equations~=0.8
Requires-Dist: langgraph~=1.0
Dynamic: license-file
